squad_df/__init__.py
squad_df/__main__.py
squad_df-0.61.dist-info/METADATA
squad_df-0.61.dist-info/WHEEL
squad_df-0.61.dist-info/top_level.txt
squad_df-0.61.dist-info/RECORD
